{
    "instaloader": {
        "node_type": "Post",
        "version": "4.2.8"
    },
    "node": {
        "__typename": "GraphVideo",
        "caption_is_edited": false,
        "comments_disabled": false,
        "dash_info": {
            "is_dash_eligible": false,
            "number_of_qualities": 0,
            "video_dash_manifest": null
        },
        "dimensions": {
            "height": 480,
            "width": 480
        },
        "display_resources": [
            {
                "config_height": 640,
                "config_width": 640,
                "src": "https://instagram.faal2-1.fna.fbcdn.net/vp/1e76b21f5c4ae7557d91aa52860a81bb/5D0AC5BE/t51.2885-15/e35/61063022_143109013414164_373048661951335802_n.jpg?_nc_ht=instagram.faal2-1.fna.fbcdn.net"
            },
            {
                "config_height": 750,
                "config_width": 750,
                "src": "https://instagram.faal2-1.fna.fbcdn.net/vp/1e76b21f5c4ae7557d91aa52860a81bb/5D0AC5BE/t51.2885-15/e35/61063022_143109013414164_373048661951335802_n.jpg?_nc_ht=instagram.faal2-1.fna.fbcdn.net"
            },
            {
                "config_height": 1080,
                "config_width": 1080,
                "src": "https://instagram.faal2-1.fna.fbcdn.net/vp/1e76b21f5c4ae7557d91aa52860a81bb/5D0AC5BE/t51.2885-15/e35/61063022_143109013414164_373048661951335802_n.jpg?_nc_ht=instagram.faal2-1.fna.fbcdn.net"
            }
        ],
        "display_url": "https://instagram.faal2-1.fna.fbcdn.net/vp/1e76b21f5c4ae7557d91aa52860a81bb/5D0AC5BE/t51.2885-15/e35/61063022_143109013414164_373048661951335802_n.jpg?_nc_ht=instagram.faal2-1.fna.fbcdn.net",
        "edge_liked_by": {
            "count": 5967
        },
        "edge_media_preview_comment": {
            "count": 33,
            "edges": [
                {
                    "node": {
                        "created_at": 1558959284,
                        "did_report_as_spam": false,
                        "edge_liked_by": {
                            "count": 0
                        },
                        "id": "18068609599045115",
                        "owner": {
                            "id": "13789913254",
                            "is_verified": false,
                            "profile_pic_url": "https://instagram.faal2-1.fna.fbcdn.net/vp/3c91ac343906bac28d1cb2f8a008a309/5D8B4493/t51.2885-19/s150x150/60028601_818546218531023_2089543843392258048_n.jpg?_nc_ht=instagram.faal2-1.fna.fbcdn.net",
                            "username": "omirbaevaajzan"
                        },
                        "text": "\ud83d\udd25\ud83d\ude02\ud83d\udc4c",
                        "viewer_has_liked": false
                    }
                },
                {
                    "node": {
                        "created_at": 1559490181,
                        "did_report_as_spam": false,
                        "edge_liked_by": {
                            "count": 0
                        },
                        "id": "18007349593203588",
                        "owner": {
                            "id": "13769267642",
                            "is_verified": false,
                            "profile_pic_url": "https://instagram.faal2-1.fna.fbcdn.net/vp/f0f834b88e6bc09d375a3e071038912b/5DA0B1A7/t51.2885-19/s150x150/60813569_450505185781401_5335211257014255616_n.jpg?_nc_ht=instagram.faal2-1.fna.fbcdn.net",
                            "username": "atabek_ibragimov_"
                        },
                        "text": "\ud83d\udc4d",
                        "viewer_has_liked": false
                    }
                }
            ]
        },
        "edge_media_preview_like": {
            "count": 5967,
            "edges": []
        },
        "edge_media_to_caption": {
            "edges": [
                {
                    "node": {
                        "text": "::::::::::::::::::::::::::::::::::::::::::::::::::::::::\n\ud83c\uddfa\ud83c\uddff Admin: @muzaffarmirzo.uz\n\u2796\u2796\u2796\u2796\u2796\u2796\u2796\u2796\u2796\u2796\n@uzbekshounews @uzbekshounews\n@uzbekshounews @uzbekshounews\n\u2796\u2796\u2796\u2796\u2796\u2796\u2796\u2796\n#uzb #tashkent #fortnite #marchforourlives #love #baby #\u0443\u0437\u0431\u0435\u043a\u0438\u0441\u0442\u0430\u043d #uzbekistan #girl #model #fashion #style #music #my5uzb #uzbekshounews #metoo #timesup ."
                    }
                }
            ]
        },
        "edge_media_to_comment": {
            "count": 33
        },
        "edge_media_to_parent_comment": {
            "count": 33,
            "edges": [
                {
                    "node": {
                        "created_at": 1558558218,
                        "did_report_as_spam": false,
                        "edge_liked_by": {
                            "count": 0
                        },
                        "edge_threaded_comments": {
                            "count": 0,
                            "edges": [],
                            "page_info": {
                                "end_cursor": null,
                                "has_next_page": false
                            }
                        },
                        "id": "18041538565088451",
                        "owner": {
                            "id": "709412761",
                            "is_verified": false,
                            "profile_pic_url": "https://instagram.faal2-1.fna.fbcdn.net/vp/988ee85c53a7bc799e7fc6ac3c30d8ed/5D830A7B/t51.2885-19/s150x150/27878318_901914276648442_5435283999306022912_n.jpg?_nc_ht=instagram.faal2-1.fna.fbcdn.net",
                            "username": "dilafruz_bekmetova_zurfalid"
                        },
                        "text": "\ud83d\udc4f\ud83d\udc4f\ud83d\udc4f",
                        "viewer_has_liked": false
                    }
                },
                {
                    "node": {
                        "created_at": 1558558669,
                        "did_report_as_spam": false,
                        "edge_liked_by": {
                            "count": 0
                        },
                        "edge_threaded_comments": {
                            "count": 0,
                            "edges": [],
                            "page_info": {
                                "end_cursor": null,
                                "has_next_page": false
                            }
                        },
                        "id": "18040709938140762",
                        "owner": {
                            "id": "7035703585",
                            "is_verified": false,
                            "profile_pic_url": "https://instagram.faal2-1.fna.fbcdn.net/vp/5c89e27afe3f9e72300a08bdf3b1dda6/5D8B12EE/t51.2885-19/s150x150/46724866_267166333976596_8662528361165225984_n.jpg?_nc_ht=instagram.faal2-1.fna.fbcdn.net",
                            "username": "doniyorziyonur"
                        },
                        "text": "\ud83d\ude02\ud83d\ude02\ud83d\ude02",
                        "viewer_has_liked": false
                    }
                },
                {
                    "node": {
                        "created_at": 1558559433,
                        "did_report_as_spam": false,
                        "edge_liked_by": {
                            "count": 0
                        },
                        "edge_threaded_comments": {
                            "count": 0,
                            "edges": [],
                            "page_info": {
                                "end_cursor": null,
                                "has_next_page": false
                            }
                        },
                        "id": "17855546452421204",
                        "owner": {
                            "id": "5261203720",
                            "is_verified": false,
                            "profile_pic_url": "https://instagram.faal2-1.fna.fbcdn.net/vp/1e356aa2b5925e3c094e2706690a91a9/5D81A8BB/t51.2885-19/s150x150/43913773_496315637538525_7301471023407300608_n.jpg?_nc_ht=instagram.faal2-1.fna.fbcdn.net",
                            "username": "yusuf930130"
                        },
                        "text": "\ud83d\udc4f\ud83d\udc4f\ud83d\udc4d",
                        "viewer_has_liked": false
                    }
                },
                {
                    "node": {
                        "created_at": 1558560408,
                        "did_report_as_spam": false,
                        "edge_liked_by": {
                            "count": 0
                        },
                        "edge_threaded_comments": {
                            "count": 0,
                            "edges": [],
                            "page_info": {
                                "end_cursor": null,
                                "has_next_page": false
                            }
                        },
                        "id": "18026817091175036",
                        "owner": {
                            "id": "5461140055",
                            "is_verified": false,
                            "profile_pic_url": "https://instagram.faal2-1.fna.fbcdn.net/vp/b3fc64cd9d400deed3940faf99a9a8d0/5DC685A0/t51.2885-19/s150x150/54732336_669683936800634_7514751222356639744_n.jpg?_nc_ht=instagram.faal2-1.fna.fbcdn.net",
                            "username": "khalim_97"
                        },
                        "text": "\ud83d\udc4f\ud83d\udc4f\ud83d\udc4f\ud83d\udc4f\ud83d\udc4f\ud83d\udc4f\ud83d\udc4f",
                        "viewer_has_liked": false
                    }
                },
                {
                    "node": {
                        "created_at": 1558563577,
                        "did_report_as_spam": false,
                        "edge_liked_by": {
                            "count": 4
                        },
                        "edge_threaded_comments": {
                            "count": 0,
                            "edges": [],
                            "page_info": {
                                "end_cursor": null,
                                "has_next_page": false
                            }
                        },
                        "id": "18027184393169276",
                        "owner": {
                            "id": "7787661259",
                            "is_verified": false,
                            "profile_pic_url": "https://instagram.faal2-1.fna.fbcdn.net/vp/54fc6ebf285a3ac901b0afa30908871d/5D9282F9/t51.2885-19/s150x150/58641577_353288701967440_8040446513488330752_n.jpg?_nc_ht=instagram.faal2-1.fna.fbcdn.net",
                            "username": "robiy.7777"
                        },
                        "text": "It bilan ot rostanam juda aqilliy jonzot\ud83d\udc4d\ud83d\udc4d\ud83d\udc4d\ud83d\udc4d",
                        "viewer_has_liked": false
                    }
                },
                {
                    "node": {
                        "created_at": 1558563769,
                        "did_report_as_spam": false,
                        "edge_liked_by": {
                            "count": 0
                        },
                        "edge_threaded_comments": {
                            "count": 1,
                            "edges": [
                                {
                                    "node": {
                                        "created_at": 1558592846,
                                        "did_report_as_spam": false,
                                        "edge_liked_by": {
                                            "count": 0
                                        },
                                        "id": "18062895076069206",
                                        "owner": {
                                            "id": "6618623923",
                                            "is_verified": false,
                                            "profile_pic_url": "https://instagram.faal2-1.fna.fbcdn.net/vp/3dd06ea563878522de77d2ac9de4200e/5DA548FF/t51.2885-19/s150x150/62591667_1229435720555885_7987812861801922560_n.jpg?_nc_ht=instagram.faal2-1.fna.fbcdn.net",
                                            "username": "abdunabiyeva___"
                                        },
                                        "text": "@sench_099 rasmni qande ochirsez video ni ham shunde",
                                        "viewer_has_liked": false
                                    }
                                }
                            ],
                            "page_info": {
                                "end_cursor": null,
                                "has_next_page": false
                            }
                        },
                        "id": "18051713437129028",
                        "owner": {
                            "id": "8397688557",
                            "is_verified": false,
                            "profile_pic_url": "https://instagram.faal2-1.fna.fbcdn.net/vp/6c00bef3b14fb1ea36419962251b0964/5D7F2E12/t51.2885-19/s150x150/64382156_888433574835994_7901094517158182912_n.jpg?_nc_ht=instagram.faal2-1.fna.fbcdn.net",
                            "username": "sench_099"
                        },
                        "text": "Qande qlip profildegi videoni ociradi ocmayapti manda",
                        "viewer_has_liked": false
                    }
                },
                {
                    "node": {
                        "created_at": 1558567915,
                        "did_report_as_spam": false,
                        "edge_liked_by": {
                            "count": 0
                        },
                        "edge_threaded_comments": {
                            "count": 0,
                            "edges": [],
                            "page_info": {
                                "end_cursor": null,
                                "has_next_page": false
                            }
                        },
                        "id": "18025071538198573",
                        "owner": {
                            "id": "13807443924",
                            "is_verified": false,
                            "profile_pic_url": "https://instagram.faal2-1.fna.fbcdn.net/vp/d38fdc6eb7246fd4007212114642d6ca/5D8F3099/t51.2885-19/s150x150/61229496_461442547959911_5815428685636829184_n.jpg?_nc_ht=instagram.faal2-1.fna.fbcdn.net",
                            "username": "brllianti"
                        },
                        "text": "HAMMA JOYDA\u00a0 FABERLIC REKLAMASIGA KO'ZIMIZ TUSHYAPTI,\ud83d\ude0e\ud83d\ude0e\ud83d\udce3 LEKIN SIZ HECH ULAR QANCHA DAROMAD TOPISHI HAQDA O'YLAB KO'RGANMISIZ\u2049\ufe0f\n\ud83e\udd14SHUNCHA ODAM FABERLIC KOMPANIYASIDA BEKORGA ISHLAMASA KERAK\u2049\ufe0f\n\ud83d\ude0dISHINGIZNI YO'QOTMAGAN HOLDA QOSHIMCHA DAROMAD OLISHNI ISTAYSIZMI?!\n\ud83d\ude0e\ud83d\ude0e\ud83d\udcb0\ud83d\udcb0\ud83d\udcb5\ud83d\udcb5 Malumot uchun telegram vatsap+79963894321\ud83d\udc4b",
                        "viewer_has_liked": false
                    }
                },
                {
                    "node": {
                        "created_at": 1558573473,
                        "did_report_as_spam": false,
                        "edge_liked_by": {
                            "count": 0
                        },
                        "edge_threaded_comments": {
                            "count": 0,
                            "edges": [],
                            "page_info": {
                                "end_cursor": null,
                                "has_next_page": false
                            }
                        },
                        "id": "18050311384112639",
                        "owner": {
                            "id": "11174841471",
                            "is_verified": false,
                            "profile_pic_url": "https://scontent-waw1-1.cdninstagram.com/vp/56d58982beb04a76d82205d35654bb05/5DA39AF1/t51.2885-19/44884218_345707102882519_2446069589734326272_n.jpg?_nc_ht=scontent-waw1-1.cdninstagram.com",
                            "username": "boliyeveldorjon98"
                        },
                        "text": "\ud83d\udc4f",
                        "viewer_has_liked": false
                    }
                },
                {
                    "node": {
                        "created_at": 1558575499,
                        "did_report_as_spam": false,
                        "edge_liked_by": {
                            "count": 0
                        },
                        "edge_threaded_comments": {
                            "count": 0,
                            "edges": [],
                            "page_info": {
                                "end_cursor": null,
                                "has_next_page": false
                            }
                        },
                        "id": "17851207903436865",
                        "owner": {
                            "id": "9544122075",
                            "is_verified": false,
                            "profile_pic_url": "https://instagram.faal2-1.fna.fbcdn.net/vp/aeafc9069b12bb8f6c755c947e79ca4d/5D975808/t51.2885-19/s150x150/49697386_2177740598979994_2352638413070401536_n.jpg?_nc_ht=instagram.faal2-1.fna.fbcdn.net",
                            "username": "taugh_girl_00"
                        },
                        "text": "\ud83d\udc4f\ud83d\udc4f\ud83d\udc4f\ud83d\udc4f\ud83d\udc4f",
                        "viewer_has_liked": false
                    }
                },
                {
                    "node": {
                        "created_at": 1558582793,
                        "did_report_as_spam": false,
                        "edge_liked_by": {
                            "count": 0
                        },
                        "edge_threaded_comments": {
                            "count": 0,
                            "edges": [],
                            "page_info": {
                                "end_cursor": null,
                                "has_next_page": false
                            }
                        },
                        "id": "17846115619447300",
                        "owner": {
                            "id": "12618487083",
                            "is_verified": false,
                            "profile_pic_url": "https://scontent-waw1-1.cdninstagram.com/vp/56d58982beb04a76d82205d35654bb05/5DA39AF1/t51.2885-19/44884218_345707102882519_2446069589734326272_n.jpg?_nc_ht=scontent-waw1-1.cdninstagram.com",
                            "username": "umidjahparov"
                        },
                        "text": "\ud83d\udc4f\ud83d\udc4f\ud83d\udc4f\ud83d\udc4f",
                        "viewer_has_liked": false
                    }
                },
                {
                    "node": {
                        "created_at": 1558586990,
                        "did_report_as_spam": false,
                        "edge_liked_by": {
                            "count": 0
                        },
                        "edge_threaded_comments": {
                            "count": 0,
                            "edges": [],
                            "page_info": {
                                "end_cursor": null,
                                "has_next_page": false
                            }
                        },
                        "id": "17844999982456137",
                        "owner": {
                            "id": "13074347197",
                            "is_verified": false,
                            "profile_pic_url": "https://instagram.faal2-1.fna.fbcdn.net/vp/6f93f716e98f7d2c6e95c5d76e13e842/5D923F0C/t51.2885-19/s150x150/57487903_631763240584235_5519856913296130048_n.jpg?_nc_ht=instagram.faal2-1.fna.fbcdn.net",
                            "username": "ak.mal3445"
                        },
                        "text": "\ud83d\ude22\ud83d\udc4f",
                        "viewer_has_liked": false
                    }
                },
                {
                    "node": {
                        "created_at": 1558587818,
                        "did_report_as_spam": false,
                        "edge_liked_by": {
                            "count": 0
                        },
                        "edge_threaded_comments": {
                            "count": 0,
                            "edges": [],
                            "page_info": {
                                "end_cursor": null,
                                "has_next_page": false
                            }
                        },
                        "id": "18069445666041912",
                        "owner": {
                            "id": "11774417921",
                            "is_verified": false,
                            "profile_pic_url": "https://instagram.faal2-1.fna.fbcdn.net/vp/d54cccb0e6414eb49e452620698654a9/5D80B9A1/t51.2885-19/s150x150/62243796_626324864511939_7100563323862646784_n.jpg?_nc_ht=instagram.faal2-1.fna.fbcdn.net",
                            "username": "kxurshidbek1995"
                        },
                        "text": "\u0428\u0443\u043d\u0430\u043a\u0430 \u0438\u0442\u0438\u043d\u0433 \u0431\u043e\u0441\u0430 \u043a\u043e\u0447\u0430\u0434\u0430 \u043a\u043e\u043c\u0435\u0441\u0430\u043d \ud83d\ude00\ud83d\ude00\ud83d\ude00",
                        "viewer_has_liked": false
                    }
                },
                {
                    "node": {
                        "created_at": 1558595426,
                        "did_report_as_spam": false,
                        "edge_liked_by": {
                            "count": 0
                        },
                        "edge_threaded_comments": {
                            "count": 0,
                            "edges": [],
                            "page_info": {
                                "end_cursor": null,
                                "has_next_page": false
                            }
                        },
                        "id": "18068835478057560",
                        "owner": {
                            "id": "9974370748",
                            "is_verified": false,
                            "profile_pic_url": "https://instagram.faal2-1.fna.fbcdn.net/vp/a36d2f0621ca9ca1df383b59dfc05225/5DC4E286/t51.2885-19/s150x150/62747759_1078560222353082_7441514891724193792_n.jpg?_nc_ht=instagram.faal2-1.fna.fbcdn.net",
                            "username": "dishrux_xan"
                        },
                        "text": "\u0428\u0443 \u043a\u0443\u0447\u0443\u043a\u0434\u0438 \u043c\u0435\u043d\u0433\u0430 \u0431\u0435\u0440\u0438\u043d\u0433\u043b\u0430\u0440 \u0441\u0442\u0440\u0435\u043b\u043a\u0430 \u0433\u0430 \u0447\u0438\u043a\u043c\u043e\u043a\u0447\u0438\u043c\u0430\u043d",
                        "viewer_has_liked": false
                    }
                },
                {
                    "node": {
                        "created_at": 1558595462,
                        "did_report_as_spam": false,
                        "edge_liked_by": {
                            "count": 0
                        },
                        "edge_threaded_comments": {
                            "count": 0,
                            "edges": [],
                            "page_info": {
                                "end_cursor": null,
                                "has_next_page": false
                            }
                        },
                        "id": "17902730095308096",
                        "owner": {
                            "id": "9974370748",
                            "is_verified": false,
                            "profile_pic_url": "https://instagram.faal2-1.fna.fbcdn.net/vp/a36d2f0621ca9ca1df383b59dfc05225/5DC4E286/t51.2885-19/s150x150/62747759_1078560222353082_7441514891724193792_n.jpg?_nc_ht=instagram.faal2-1.fna.fbcdn.net",
                            "username": "dishrux_xan"
                        },
                        "text": "\ud83e\udd28\ud83e\udd28\ud83e\udd28\u043c\u0435\u043d\u0438\u043c\u0447\u0430 \u0448\u0443 \u043a\u0443\u0447\u0443\u043a\u0434\u0438 \u043a\u0438\u0437 \u0451\u043d\u043b\u0430\u0433\u0430\u043d \u0431\u0443\u043b\u0441\u0430 \u043a\u0435\u0440\u0430\u043a\ud83d\ude00\ud83d\ude00\ud83d\ude00",
                        "viewer_has_liked": false
                    }
                },
                {
                    "node": {
                        "created_at": 1558600128,
                        "did_report_as_spam": false,
                        "edge_liked_by": {
                            "count": 0
                        },
                        "edge_threaded_comments": {
                            "count": 0,
                            "edges": [],
                            "page_info": {
                                "end_cursor": null,
                                "has_next_page": false
                            }
                        },
                        "id": "18068282821013478",
                        "owner": {
                            "id": "8906756845",
                            "is_verified": false,
                            "profile_pic_url": "https://instagram.faal2-1.fna.fbcdn.net/vp/0e7f938741163bdf7a6e6067fd274183/5DC18F6D/t51.2885-19/s150x150/58423573_433364024162799_7336896502075228160_n.jpg?_nc_ht=instagram.faal2-1.fna.fbcdn.net",
                            "username": "bobirmirzo_o1"
                        },
                        "text": "Itiyam iti ekan",
                        "viewer_has_liked": false
                    }
                },
                {
                    "node": {
                        "created_at": 1558600341,
                        "did_report_as_spam": false,
                        "edge_liked_by": {
                            "count": 0
                        },
                        "edge_threaded_comments": {
                            "count": 0,
                            "edges": [],
                            "page_info": {
                                "end_cursor": null,
                                "has_next_page": false
                            }
                        },
                        "id": "17991986248229459",
                        "owner": {
                            "id": "13775030342",
                            "is_verified": false,
                            "profile_pic_url": "https://instagram.faal2-1.fna.fbcdn.net/vp/629b7e5095e2ca55685f68b502c15bed/5D804A55/t51.2885-19/s150x150/62104131_339583246718911_9074633728801636352_n.jpg?_nc_ht=instagram.faal2-1.fna.fbcdn.net",
                            "username": "yarashovxu"
                        },
                        "text": "\ud83d\udc4f\ud83d\udc4f",
                        "viewer_has_liked": false
                    }
                },
                {
                    "node": {
                        "created_at": 1558601828,
                        "did_report_as_spam": false,
                        "edge_liked_by": {
                            "count": 0
                        },
                        "edge_threaded_comments": {
                            "count": 0,
                            "edges": [],
                            "page_info": {
                                "end_cursor": null,
                                "has_next_page": false
                            }
                        },
                        "id": "17883777100353201",
                        "owner": {
                            "id": "5739965747",
                            "is_verified": false,
                            "profile_pic_url": "https://instagram.faal2-1.fna.fbcdn.net/vp/071c67a9d59466998520af6f04210828/5D8AA305/t51.2885-19/s150x150/59835224_359831681179211_2823409980248424448_n.jpg?_nc_ht=instagram.faal2-1.fna.fbcdn.net",
                            "username": "asadbek_19_09"
                        },
                        "text": "Zor ciqipti bu video",
                        "viewer_has_liked": false
                    }
                },
                {
                    "node": {
                        "created_at": 1558602308,
                        "did_report_as_spam": false,
                        "edge_liked_by": {
                            "count": 0
                        },
                        "edge_threaded_comments": {
                            "count": 0,
                            "edges": [],
                            "page_info": {
                                "end_cursor": null,
                                "has_next_page": false
                            }
                        },
                        "id": "18069006043054899",
                        "owner": {
                            "id": "8136893242",
                            "is_verified": false,
                            "profile_pic_url": "https://instagram.faal2-1.fna.fbcdn.net/vp/616233ce804ea8526f295f6d54fb0c7d/5DA1AAF0/t51.2885-19/s150x150/35934520_905022169701258_8157599108060676096_n.jpg?_nc_ht=instagram.faal2-1.fna.fbcdn.net",
                            "username": "dubaidreamjobs"
                        },
                        "text": "\u041f\u043e\u043c\u043e\u0436\u0435\u043c \u043d\u0430\u0439\u0442\u0438 \u0440\u0430\u0431\u043e\u0442\u0443 \u0437\u0430 \u0433\u0440\u0430\u043d\u0438\u0446\u0435\u0439!\n\u0412 \u041e\u0431\u044a\u0435\u0434\u0438\u043d\u0451\u043d\u043d\u044b\u0445 \u0410\u0440\u0430\u0431\u0441\u043a\u0438\u0445 \u042d\u043c\u0438\u0440\u0430\u0442\u0430\u0445\n\u0412 \u041a\u0430\u0442\u0430\u0440\u0435\n\u0412 \u041a\u0443\u0432\u0435\u0439\u0442\u0435 \n\u041d\u0430 \u041c\u0430\u043b\u044c\u0434\u0438\u0432\u0430\u0445 \n\u041a\u043e\u043d\u0441\u0443\u043b\u044c\u0442\u0430\u0446\u0438\u043e\u043d\u043d\u044b\u0435 \u0443\u0441\u043b\u0443\u0433\u0438\n\nhttps://t.me/DMdreamjobs",
                        "viewer_has_liked": false
                    }
                },
                {
                    "node": {
                        "created_at": 1558607720,
                        "did_report_as_spam": false,
                        "edge_liked_by": {
                            "count": 0
                        },
                        "edge_threaded_comments": {
                            "count": 0,
                            "edges": [],
                            "page_info": {
                                "end_cursor": null,
                                "has_next_page": false
                            }
                        },
                        "id": "18004429948204160",
                        "owner": {
                            "id": "11220576696",
                            "is_verified": false,
                            "profile_pic_url": "https://scontent-waw1-1.cdninstagram.com/vp/56d58982beb04a76d82205d35654bb05/5DA39AF1/t51.2885-19/44884218_345707102882519_2446069589734326272_n.jpg?_nc_ht=scontent-waw1-1.cdninstagram.com",
                            "username": "asalbonu86"
                        },
                        "text": "\ud83d\udc4f\ud83d\udc4f\ud83d\udc4f",
                        "viewer_has_liked": false
                    }
                },
                {
                    "node": {
                        "created_at": 1558640479,
                        "did_report_as_spam": false,
                        "edge_liked_by": {
                            "count": 0
                        },
                        "edge_threaded_comments": {
                            "count": 0,
                            "edges": [],
                            "page_info": {
                                "end_cursor": null,
                                "has_next_page": false
                            }
                        },
                        "id": "17851307890438773",
                        "owner": {
                            "id": "8079519682",
                            "is_verified": false,
                            "profile_pic_url": "https://instagram.faal2-1.fna.fbcdn.net/vp/1d5ed1d8a562744c6a59ce2e5eaee294/5D8C84F2/t51.2885-19/s150x150/50015910_1153776778129990_8049593904770580480_n.jpg?_nc_ht=instagram.faal2-1.fna.fbcdn.net",
                            "username": "islam__jaan"
                        },
                        "text": "Imkoni boganda wu klib u.n 1000000 like bosardim",
                        "viewer_has_liked": false
                    }
                },
                {
                    "node": {
                        "created_at": 1558679651,
                        "did_report_as_spam": false,
                        "edge_liked_by": {
                            "count": 0
                        },
                        "edge_threaded_comments": {
                            "count": 0,
                            "edges": [],
                            "page_info": {
                                "end_cursor": null,
                                "has_next_page": false
                            }
                        },
                        "id": "17991366790232416",
                        "owner": {
                            "id": "460824900",
                            "is_verified": false,
                            "profile_pic_url": "https://instagram.faal2-1.fna.fbcdn.net/vp/12d4461c42e9a57e31ef5ff914c978f7/5DA0C2A3/t51.2885-19/s150x150/60010616_2326901947590553_1959100515472113664_n.jpg?_nc_ht=instagram.faal2-1.fna.fbcdn.net",
                            "username": "bakhromov"
                        },
                        "text": "\u041d\u0438\u043c\u0430 \u043a\u0438\u043d\u043e?",
                        "viewer_has_liked": false
                    }
                },
                {
                    "node": {
                        "created_at": 1558814162,
                        "did_report_as_spam": false,
                        "edge_liked_by": {
                            "count": 0
                        },
                        "edge_threaded_comments": {
                            "count": 0,
                            "edges": [],
                            "page_info": {
                                "end_cursor": null,
                                "has_next_page": false
                            }
                        },
                        "id": "18069565363034079",
                        "owner": {
                            "id": "13314279532",
                            "is_verified": false,
                            "profile_pic_url": "https://instagram.faal2-1.fna.fbcdn.net/vp/9523bcd06028d04e7bf541f23889914e/5D8D0465/t51.2885-19/s150x150/60608900_2637970402939640_7560933446617399296_n.jpg?_nc_ht=instagram.faal2-1.fna.fbcdn.net",
                            "username": "guli_erkayeva"
                        },
                        "text": "\u0418\u0442\ud83d\udc36\u0438\u043d\u0441\u043e\u043d\u0433\u0430 \u0434\u0443\u0441\u0442, \u0432\u0430\u0444\u043e\u0434\u043e\u0440\u043b\u0438\u0433\u0438\u043d\u0438 \u044f\u043d\u0430 \u0431\u0438\u0440 \u0431\u043e\u0440 \u0438\u0441\u0431\u043e\u0442\u043b\u0430\u0434\u0438\ud83d\udc36\ud83d\udc15",
                        "viewer_has_liked": false
                    }
                },
                {
                    "node": {
                        "created_at": 1558959284,
                        "did_report_as_spam": false,
                        "edge_liked_by": {
                            "count": 0
                        },
                        "edge_threaded_comments": {
                            "count": 0,
                            "edges": [],
                            "page_info": {
                                "end_cursor": null,
                                "has_next_page": false
                            }
                        },
                        "id": "18068609599045115",
                        "owner": {
                            "id": "13789913254",
                            "is_verified": false,
                            "profile_pic_url": "https://instagram.faal2-1.fna.fbcdn.net/vp/3c91ac343906bac28d1cb2f8a008a309/5D8B4493/t51.2885-19/s150x150/60028601_818546218531023_2089543843392258048_n.jpg?_nc_ht=instagram.faal2-1.fna.fbcdn.net",
                            "username": "omirbaevaajzan"
                        },
                        "text": "\ud83d\udd25\ud83d\ude02\ud83d\udc4c",
                        "viewer_has_liked": false
                    }
                },
                {
                    "node": {
                        "created_at": 1559490181,
                        "did_report_as_spam": false,
                        "edge_liked_by": {
                            "count": 0
                        },
                        "edge_threaded_comments": {
                            "count": 0,
                            "edges": [],
                            "page_info": {
                                "end_cursor": null,
                                "has_next_page": false
                            }
                        },
                        "id": "18007349593203588",
                        "owner": {
                            "id": "13769267642",
                            "is_verified": false,
                            "profile_pic_url": "https://instagram.faal2-1.fna.fbcdn.net/vp/f0f834b88e6bc09d375a3e071038912b/5DA0B1A7/t51.2885-19/s150x150/60813569_450505185781401_5335211257014255616_n.jpg?_nc_ht=instagram.faal2-1.fna.fbcdn.net",
                            "username": "atabek_ibragimov_"
                        },
                        "text": "\ud83d\udc4d",
                        "viewer_has_liked": false
                    }
                }
            ],
            "page_info": {
                "end_cursor": "QVFBNGRZSXdfeUswaWpFeUZYRGpGZ3Byck5DSGtVQ19MMlkxSVJBajUwYlU4QmlLaUZ5bFRHYzhpdUdjVE8zNE1vS2xvMWlBVVpsTTQwcnZOeUlUN0R2aA==",
                "has_next_page": true
            }
        },
        "edge_media_to_sponsor_user": {
            "edges": []
        },
        "edge_media_to_tagged_user": {
            "edges": []
        },
        "edge_web_media_to_related_media": {
            "edges": []
        },
        "encoding_status": null,
        "gating_info": null,
        "has_ranked_comments": false,
        "id": "2049540599794936206",
        "is_ad": false,
        "is_published": true,
        "is_video": true,
        "location": null,
        "media_preview": null,
        "owner": {
            "blocked_by_viewer": false,
            "followed_by_viewer": false,
            "full_name": "UZBEK SHOU BIZNES \ud83d\udc97 733k",
            "has_blocked_viewer": false,
            "id": "4132821798",
            "is_private": false,
            "is_unpublished": false,
            "is_verified": false,
            "profile_pic_url": "https://instagram.faal2-1.fna.fbcdn.net/vp/9e11d0617cefa5fb45a829a841bfca52/5D939975/t51.2885-19/s150x150/60774211_2202590200052328_4628725708468781056_n.jpg?_nc_ht=instagram.faal2-1.fna.fbcdn.net",
            "requested_by_viewer": false,
            "username": "uzbekshounews"
        },
        "product_type": "feed",
        "shortcode": "BxxblELhKmO",
        "should_log_client_event": false,
        "taken_at_timestamp": 1558544334,
        "thumbnail_resources": [
            {
                "config_height": 150,
                "config_width": 150,
                "src": "https://instagram.faal2-1.fna.fbcdn.net/vp/69d8f1f3e5b3c0524e1db087d50ba958/5D0A7BAC/t51.2885-15/e35/s150x150/61063022_143109013414164_373048661951335802_n.jpg?_nc_ht=instagram.faal2-1.fna.fbcdn.net"
            },
            {
                "config_height": 240,
                "config_width": 240,
                "src": "https://instagram.faal2-1.fna.fbcdn.net/vp/0299c5923037a38d6528bd0aec5c6685/5D0A7899/t51.2885-15/e35/s240x240/61063022_143109013414164_373048661951335802_n.jpg?_nc_ht=instagram.faal2-1.fna.fbcdn.net"
            },
            {
                "config_height": 320,
                "config_width": 320,
                "src": "https://instagram.faal2-1.fna.fbcdn.net/vp/a8aab426f3ad2c32c23b75653b1ed9b5/5D0A5B61/t51.2885-15/e35/s320x320/61063022_143109013414164_373048661951335802_n.jpg?_nc_ht=instagram.faal2-1.fna.fbcdn.net"
            },
            {
                "config_height": 480,
                "config_width": 480,
                "src": "https://instagram.faal2-1.fna.fbcdn.net/vp/1e76b21f5c4ae7557d91aa52860a81bb/5D0AC5BE/t51.2885-15/e35/61063022_143109013414164_373048661951335802_n.jpg?_nc_ht=instagram.faal2-1.fna.fbcdn.net"
            },
            {
                "config_height": 640,
                "config_width": 640,
                "src": "https://instagram.faal2-1.fna.fbcdn.net/vp/1e76b21f5c4ae7557d91aa52860a81bb/5D0AC5BE/t51.2885-15/e35/61063022_143109013414164_373048661951335802_n.jpg?_nc_ht=instagram.faal2-1.fna.fbcdn.net"
            }
        ],
        "thumbnail_src": "https://instagram.faal2-1.fna.fbcdn.net/vp/1e76b21f5c4ae7557d91aa52860a81bb/5D0AC5BE/t51.2885-15/e35/61063022_143109013414164_373048661951335802_n.jpg?_nc_ht=instagram.faal2-1.fna.fbcdn.net",
        "title": "",
        "tracking_token": "eyJ2ZXJzaW9uIjo1LCJwYXlsb2FkIjp7ImlzX2FuYWx5dGljc190cmFja2VkIjp0cnVlLCJ1dWlkIjoiNjNlMTcyYmM3NjE3NDcwMjhkOWVmNmNhMzEyZmYwM2EyMDQ5NTQwNTk5Nzk0OTM2MjA2In0sInNpZ25hdHVyZSI6IiJ9",
        "video_duration": 57.3,
        "video_url": "https://scontent.cdninstagram.com/vp/cd30a203b61a00633cf08c9bb2aa59b0/5D0A23E1/t50.2886-16/61116964_1036037899918339_1881417648147791872_n.mp4?_nc_ht=scontent.cdninstagram.com",
        "video_view_count": 67160,
        "viewer_can_reshare": true,
        "viewer_has_liked": false,
        "viewer_has_saved": false,
        "viewer_has_saved_to_collection": false,
        "viewer_in_photo_of_you": false
    }
}