{
    "instaloader": {
        "node_type": "Post",
        "version": "4.2.8"
    },
    "node": {
        "__typename": "GraphImage",
        "accessibility_caption": "Image may contain: one or more people and closeup",
        "comments_disabled": false,
        "dimensions": {
            "height": 1080,
            "width": 1080
        },
        "display_url": "https://instagram.faal2-1.fna.fbcdn.net/vp/bb52b868d951838a4200c933c2db0bf3/5D961F5B/t51.2885-15/e35/s1080x1080/61239070_2471386179763159_5183206424063542308_n.jpg?_nc_ht=instagram.faal2-1.fna.fbcdn.net",
        "edge_liked_by": {
            "count": 31
        },
        "edge_media_preview_like": {
            "count": 31
        },
        "edge_media_to_caption": {
            "edges": [
                {
                    "node": {
                        "text": "\ud83e\udde1\ud83d\udc99Reflecting on Allah\u2019s Mercy. It is only Him who allowed me to turn my pain into purpose, my passion into my profession, and my voice and experience to make a difference.\n.\n.\n\ud83e\udde1\ud83d\udc99Today will be Terrific, as I use my voice to inspire others who have face adversity similar to mine. Hope to see you at the HIV Prevention & Education Summit today!\n.\n.\n#metoo #trauma #mentalhealthawareness #mentalhealth #hivpositive #teenlife #teens #bodysafety #"
                    }
                }
            ]
        },
        "edge_media_to_comment": {
            "count": 4
        },
        "id": "2063942665461707106",
        "is_video": false,
        "owner": {
            "id": "48868814"
        },
        "shortcode": "BykmOtDnjFi",
        "taken_at_timestamp": 1560261160,
        "thumbnail_resources": [
            {
                "config_height": 150,
                "config_width": 150,
                "src": "https://instagram.faal2-1.fna.fbcdn.net/vp/9f7b04b83cdc16ab61c1f23ee01bf5a7/5D7E851A/t51.2885-15/e35/s150x150/61239070_2471386179763159_5183206424063542308_n.jpg?_nc_ht=instagram.faal2-1.fna.fbcdn.net"
            },
            {
                "config_height": 240,
                "config_width": 240,
                "src": "https://instagram.faal2-1.fna.fbcdn.net/vp/32f1e0ca09080f92bb6819ded1939ae2/5D933E1C/t51.2885-15/e35/s240x240/61239070_2471386179763159_5183206424063542308_n.jpg?_nc_ht=instagram.faal2-1.fna.fbcdn.net"
            },
            {
                "config_height": 320,
                "config_width": 320,
                "src": "https://instagram.faal2-1.fna.fbcdn.net/vp/f39267c2eb931504da3b8c8fd958d8c5/5D8DB262/t51.2885-15/e35/s320x320/61239070_2471386179763159_5183206424063542308_n.jpg?_nc_ht=instagram.faal2-1.fna.fbcdn.net"
            },
            {
                "config_height": 480,
                "config_width": 480,
                "src": "https://instagram.faal2-1.fna.fbcdn.net/vp/7c4953711a098ead467ff150c8ccdda9/5DA55825/t51.2885-15/e35/s480x480/61239070_2471386179763159_5183206424063542308_n.jpg?_nc_ht=instagram.faal2-1.fna.fbcdn.net"
            },
            {
                "config_height": 640,
                "config_width": 640,
                "src": "https://instagram.faal2-1.fna.fbcdn.net/vp/a4ac93610aa1903228e2e332260aead9/5D939B9F/t51.2885-15/sh0.08/e35/s640x640/61239070_2471386179763159_5183206424063542308_n.jpg?_nc_ht=instagram.faal2-1.fna.fbcdn.net"
            }
        ],
        "thumbnail_src": "https://instagram.faal2-1.fna.fbcdn.net/vp/a4ac93610aa1903228e2e332260aead9/5D939B9F/t51.2885-15/sh0.08/e35/s640x640/61239070_2471386179763159_5183206424063542308_n.jpg?_nc_ht=instagram.faal2-1.fna.fbcdn.net"
    }
}