{
    "instaloader": {
        "node_type": "Post",
        "version": "4.2.8"
    },
    "node": {
        "__typename": "GraphVideo",
        "caption_is_edited": true,
        "comments_disabled": false,
        "dash_info": {
            "is_dash_eligible": false,
            "number_of_qualities": 0,
            "video_dash_manifest": null
        },
        "dimensions": {
            "height": 422,
            "width": 750
        },
        "display_resources": [
            {
                "config_height": 360,
                "config_width": 640,
                "src": "https://instagram.faal2-1.fna.fbcdn.net/vp/256010f538217f2c08e0b31ff18c5cac/5D09EEC0/t51.2885-15/sh0.08/e35/s640x640/61342316_2412669592087766_193945895401469761_n.jpg?_nc_ht=instagram.faal2-1.fna.fbcdn.net"
            },
            {
                "config_height": 422,
                "config_width": 750,
                "src": "https://instagram.faal2-1.fna.fbcdn.net/vp/911283f9bc3f1197a70858fa7060c086/5D09A165/t51.2885-15/e35/61342316_2412669592087766_193945895401469761_n.jpg?_nc_ht=instagram.faal2-1.fna.fbcdn.net"
            },
            {
                "config_height": 609,
                "config_width": 1080,
                "src": "https://instagram.faal2-1.fna.fbcdn.net/vp/911283f9bc3f1197a70858fa7060c086/5D09A165/t51.2885-15/e35/61342316_2412669592087766_193945895401469761_n.jpg?_nc_ht=instagram.faal2-1.fna.fbcdn.net"
            }
        ],
        "display_url": "https://instagram.faal2-1.fna.fbcdn.net/vp/911283f9bc3f1197a70858fa7060c086/5D09A165/t51.2885-15/e35/61342316_2412669592087766_193945895401469761_n.jpg?_nc_ht=instagram.faal2-1.fna.fbcdn.net",
        "edge_liked_by": {
            "count": 1093
        },
        "edge_media_preview_comment": {
            "count": 61,
            "edges": [
                {
                    "node": {
                        "created_at": 1559994565,
                        "did_report_as_spam": false,
                        "edge_liked_by": {
                            "count": 0
                        },
                        "id": "17950165846287829",
                        "owner": {
                            "id": "8431578811",
                            "is_verified": false,
                            "profile_pic_url": "https://instagram.faal2-1.fna.fbcdn.net/vp/f280376716c41fdc78960b09a7cbb64c/5D8D7E8C/t51.2885-19/s150x150/64333902_2329315697122129_538111216950706176_n.jpg?_nc_ht=instagram.faal2-1.fna.fbcdn.net",
                            "username": "reyshapratiwi_"
                        },
                        "text": "@ruli.agustian lobi mnjalita",
                        "viewer_has_liked": false
                    }
                },
                {
                    "node": {
                        "created_at": 1560064100,
                        "did_report_as_spam": false,
                        "edge_liked_by": {
                            "count": 0
                        },
                        "id": "18075609217048717",
                        "owner": {
                            "id": "1431592800",
                            "is_verified": false,
                            "profile_pic_url": "https://instagram.faal2-1.fna.fbcdn.net/vp/213ab6abf01c7b5070c6288b68450913/5DC749EE/t51.2885-19/s150x150/62153706_367907917416288_1029252504048631808_n.jpg?_nc_ht=instagram.faal2-1.fna.fbcdn.net",
                            "username": "didisandhyka16"
                        },
                        "text": "@kartikajylo jawabnnya bgus, yg salah penerjemahnya. Mungkin sama kasus dgn bunga waktu interview katanya jawaban bunga bgus tpi penerjemah nya itu kurang sreg, makanya pas bunga selesai interview tuh bunga senang dan yakin dgn jawabnnya dan pas disorot ke penerjemah itu biasa aja",
                        "viewer_has_liked": false
                    }
                }
            ]
        },
        "edge_media_preview_like": {
            "count": 1093,
            "edges": []
        },
        "edge_media_to_caption": {
            "edges": [
                {
                    "node": {
                        "text": "#Throwback #MissUniverse2018\n.\n@hhennie.official berhasil melenggang mulus sampai ke Babak Top 5\nDibabak Top 5 @hhennie.official mendapatkan pertanyaan Seputar #MeToo ia menjawab dengan 'Native Language' di saat itu ada sedikit kendala Ketika Sang Penerjemah (Interprenter) menerjemahkan jawabannya @hhennie.official jawaban yang diterjemahkan Ternyata Kurang Tepat, hal ini dikemukakan oleh Channel YouTube 'The Madlang People Present'\nTapi apa kata Kejadian tidak dapat terulang lagi\n.\n#MissUniverse #MissUniverseVietnam #MissUniverseVietnam2018 #hhennie #Vietnam"
                    }
                }
            ]
        },
        "edge_media_to_comment": {
            "count": 61
        },
        "edge_media_to_parent_comment": {
            "count": 61,
            "edges": [
                {
                    "node": {
                        "created_at": 1559569749,
                        "did_report_as_spam": false,
                        "edge_liked_by": {
                            "count": 2
                        },
                        "edge_threaded_comments": {
                            "count": 5,
                            "edges": [
                                {
                                    "node": {
                                        "created_at": 1559575503,
                                        "did_report_as_spam": false,
                                        "edge_liked_by": {
                                            "count": 0
                                        },
                                        "id": "17994664768232661",
                                        "owner": {
                                            "id": "5999607124",
                                            "is_verified": false,
                                            "profile_pic_url": "https://instagram.faal2-1.fna.fbcdn.net/vp/3adca30ff36cedaa03ab1381d1072d03/5D96E5B7/t51.2885-19/s150x150/33361125_375783069585926_1548392034409119744_n.jpg?_nc_ht=instagram.faal2-1.fna.fbcdn.net",
                                            "username": "vionariverva17"
                                        },
                                        "text": "@h_tembus parah y jadi yg salah siapa ceu",
                                        "viewer_has_liked": false
                                    }
                                },
                                {
                                    "node": {
                                        "created_at": 1559686571,
                                        "did_report_as_spam": false,
                                        "edge_liked_by": {
                                            "count": 1
                                        },
                                        "id": "18038613472178234",
                                        "owner": {
                                            "id": "3185508939",
                                            "is_verified": false,
                                            "profile_pic_url": "https://instagram.faal2-1.fna.fbcdn.net/vp/9870bf654140715654c451f705f4604b/5DA162F7/t51.2885-19/s150x150/55765622_780951735612180_6800447162590167040_n.jpg?_nc_ht=instagram.faal2-1.fna.fbcdn.net",
                                            "username": "h_tembus"
                                        },
                                        "text": "@vionariverva17 si penerjemahnya",
                                        "viewer_has_liked": false
                                    }
                                },
                                {
                                    "node": {
                                        "created_at": 1559686658,
                                        "did_report_as_spam": false,
                                        "edge_liked_by": {
                                            "count": 0
                                        },
                                        "id": "18038579857155204",
                                        "owner": {
                                            "id": "3185508939",
                                            "is_verified": false,
                                            "profile_pic_url": "https://instagram.faal2-1.fna.fbcdn.net/vp/9870bf654140715654c451f705f4604b/5DA162F7/t51.2885-19/s150x150/55765622_780951735612180_6800447162590167040_n.jpg?_nc_ht=instagram.faal2-1.fna.fbcdn.net",
                                            "username": "h_tembus"
                                        },
                                        "text": "@carlabrucha nggak masalah itukan bukan forum debat!!!lagian dia juga ditanya soal bagaimana pendapat dia jadi apapun jawabannya begitulah adanya sesuai dengan pendapat dia",
                                        "viewer_has_liked": false
                                    }
                                }
                            ],
                            "page_info": {
                                "end_cursor": null,
                                "has_next_page": false
                            }
                        },
                        "id": "18050782333125550",
                        "owner": {
                            "id": "3185508939",
                            "is_verified": false,
                            "profile_pic_url": "https://instagram.faal2-1.fna.fbcdn.net/vp/9870bf654140715654c451f705f4604b/5DA162F7/t51.2885-19/s150x150/55765622_780951735612180_6800447162590167040_n.jpg?_nc_ht=instagram.faal2-1.fna.fbcdn.net",
                            "username": "h_tembus"
                        },
                        "text": "@hhennie.official bilang kalau #metoo sudah terlalu jauh tapi sang penerjemahnya bilang \"she @hhennie.official does not think that it has gone too far\"",
                        "viewer_has_liked": false
                    }
                },
                {
                    "node": {
                        "created_at": 1559577379,
                        "did_report_as_spam": false,
                        "edge_liked_by": {
                            "count": 0
                        },
                        "edge_threaded_comments": {
                            "count": 9,
                            "edges": [
                                {
                                    "node": {
                                        "created_at": 1559888612,
                                        "did_report_as_spam": false,
                                        "edge_liked_by": {
                                            "count": 0
                                        },
                                        "id": "18065100988079331",
                                        "owner": {
                                            "id": "9979057198",
                                            "is_verified": false,
                                            "profile_pic_url": "https://instagram.fala4-1.fna.fbcdn.net/vp/9a1a8a931ca1249b57a91917564f2856/5DA39AF1/t51.2885-19/44884218_345707102882519_2446069589734326272_n.jpg?_nc_ht=instagram.fala4-1.fna.fbcdn.net",
                                            "username": "shavanazta"
                                        },
                                        "text": "@decsonrobinson ga nyambung? Emng lu ngerti apa itu #MeToo ?",
                                        "viewer_has_liked": false
                                    }
                                },
                                {
                                    "node": {
                                        "created_at": 1559934436,
                                        "did_report_as_spam": false,
                                        "edge_liked_by": {
                                            "count": 1
                                        },
                                        "id": "17863028296409971",
                                        "owner": {
                                            "id": "9123215165",
                                            "is_verified": false,
                                            "profile_pic_url": "https://instagram.faal2-1.fna.fbcdn.net/vp/500b5e23c53391d7ccec54ee8eba8f2e/5D8F7A8A/t51.2885-19/s150x150/62151292_2285172608219001_4205179733366800384_n.jpg?_nc_ht=instagram.faal2-1.fna.fbcdn.net",
                                            "username": "decsonrobinson"
                                        },
                                        "text": "@shavanazta wkk .. ngerti lah .. anak tk juga tahu kali \ud83d\ude02",
                                        "viewer_has_liked": false
                                    }
                                },
                                {
                                    "node": {
                                        "created_at": 1559940737,
                                        "did_report_as_spam": false,
                                        "edge_liked_by": {
                                            "count": 0
                                        },
                                        "id": "17995572319235959",
                                        "owner": {
                                            "id": "9979057198",
                                            "is_verified": false,
                                            "profile_pic_url": "https://instagram.fala4-1.fna.fbcdn.net/vp/9a1a8a931ca1249b57a91917564f2856/5DA39AF1/t51.2885-19/44884218_345707102882519_2446069589734326272_n.jpg?_nc_ht=instagram.fala4-1.fna.fbcdn.net",
                                            "username": "shavanazta"
                                        },
                                        "text": "@decsonrobinson OH",
                                        "viewer_has_liked": false
                                    }
                                }
                            ],
                            "page_info": {
                                "end_cursor": "QVFEZFBVcjNobmZEZVI3a1N4REU2S0plMm9iUXRqYWNfRGRDSVRZTzN0VjM4dVJvT2xNNnFOb0NEZVJ0WEZwU1c0VG9GRjZaeHZmZXY1enpYSWtqd21PbQ==",
                                "has_next_page": true
                            }
                        },
                        "id": "17891791270339957",
                        "owner": {
                            "id": "9123215165",
                            "is_verified": false,
                            "profile_pic_url": "https://instagram.faal2-1.fna.fbcdn.net/vp/500b5e23c53391d7ccec54ee8eba8f2e/5D8F7A8A/t51.2885-19/s150x150/62151292_2285172608219001_4205179733366800384_n.jpg?_nc_ht=instagram.faal2-1.fna.fbcdn.net",
                            "username": "decsonrobinson"
                        },
                        "text": "Gak nyambung bngt .. jawaban kayak anak tk yg baru bljar ngomong .. Heran english brantakan gini top 5 @pagent.id",
                        "viewer_has_liked": false
                    }
                },
                {
                    "node": {
                        "created_at": 1559584032,
                        "did_report_as_spam": false,
                        "edge_liked_by": {
                            "count": 9
                        },
                        "edge_threaded_comments": {
                            "count": 3,
                            "edges": [
                                {
                                    "node": {
                                        "created_at": 1559640008,
                                        "did_report_as_spam": false,
                                        "edge_liked_by": {
                                            "count": 4
                                        },
                                        "id": "17949085591286715",
                                        "owner": {
                                            "id": "11863698641",
                                            "is_verified": false,
                                            "profile_pic_url": "https://instagram.faal2-1.fna.fbcdn.net/vp/c138ce1e6eb94542a6110606dd1f4d58/5D806E5A/t51.2885-19/s150x150/54511108_430300071048319_8306203374479474688_n.jpg?_nc_ht=instagram.faal2-1.fna.fbcdn.net",
                                            "username": "frd.andini"
                                        },
                                        "text": "@fajaryusufdirgantara mata nya kosong tatapannya.. Kebingungan",
                                        "viewer_has_liked": false
                                    }
                                },
                                {
                                    "node": {
                                        "created_at": 1559989584,
                                        "did_report_as_spam": false,
                                        "edge_liked_by": {
                                            "count": 1
                                        },
                                        "id": "18074495329034119",
                                        "owner": {
                                            "id": "11822085067",
                                            "is_verified": false,
                                            "profile_pic_url": "https://instagram.fala4-1.fna.fbcdn.net/vp/9a1a8a931ca1249b57a91917564f2856/5DA39AF1/t51.2885-19/44884218_345707102882519_2446069589734326272_n.jpg?_nc_ht=instagram.fala4-1.fna.fbcdn.net",
                                            "username": "altanovadanang"
                                        },
                                        "text": "@fajaryusufdirgantara orang place karena nyogok",
                                        "viewer_has_liked": false
                                    }
                                },
                                {
                                    "node": {
                                        "created_at": 1559994216,
                                        "did_report_as_spam": false,
                                        "edge_liked_by": {
                                            "count": 3
                                        },
                                        "id": "17962172776277009",
                                        "owner": {
                                            "id": "8431578811",
                                            "is_verified": false,
                                            "profile_pic_url": "https://instagram.faal2-1.fna.fbcdn.net/vp/f280376716c41fdc78960b09a7cbb64c/5D8D7E8C/t51.2885-19/s150x150/64333902_2329315697122129_538111216950706176_n.jpg?_nc_ht=instagram.faal2-1.fna.fbcdn.net",
                                            "username": "reyshapratiwi_"
                                        },
                                        "text": "@altanovadanang dia place karena cerita kehidupan nya yang bisa meluluhkan hati oma gulali cerita dia keluarga miskin ,minoritas ,dan berusahan untuk pendidikan nya ,catwalk nya bagus ada mangap2 nya juga",
                                        "viewer_has_liked": false
                                    }
                                }
                            ],
                            "page_info": {
                                "end_cursor": null,
                                "has_next_page": false
                            }
                        },
                        "id": "17995046011233694",
                        "owner": {
                            "id": "3260065960",
                            "is_verified": false,
                            "profile_pic_url": "https://instagram.faal2-1.fna.fbcdn.net/vp/83f5959bc6a2a25fcf22f5dd5fb10447/5D86A004/t51.2885-19/s150x150/43817891_268197860556847_2299977118974476288_n.jpg?_nc_ht=instagram.faal2-1.fna.fbcdn.net",
                            "username": "fajaryusufdirgantara"
                        },
                        "text": "Top 5 yg tak layak... cm menang rambut bondol dan catwalk doang.. otak kosong..",
                        "viewer_has_liked": false
                    }
                },
                {
                    "node": {
                        "created_at": 1559585303,
                        "did_report_as_spam": false,
                        "edge_liked_by": {
                            "count": 1
                        },
                        "edge_threaded_comments": {
                            "count": 3,
                            "edges": [
                                {
                                    "node": {
                                        "created_at": 1559730833,
                                        "did_report_as_spam": false,
                                        "edge_liked_by": {
                                            "count": 1
                                        },
                                        "id": "17895340744330446",
                                        "owner": {
                                            "id": "3225895476",
                                            "is_verified": false,
                                            "profile_pic_url": "https://instagram.faal2-1.fna.fbcdn.net/vp/3c530a1a23033b9255b5c509ed02fdbe/5D86A285/t51.2885-19/s150x150/62638201_2398261580457977_6956338120199503872_n.jpg?_nc_ht=instagram.faal2-1.fna.fbcdn.net",
                                            "username": "yendriamandar"
                                        },
                                        "text": "@kartikajylo bener kok jawab nya dan nuambung banget",
                                        "viewer_has_liked": false
                                    }
                                },
                                {
                                    "node": {
                                        "created_at": 1559888520,
                                        "did_report_as_spam": false,
                                        "edge_liked_by": {
                                            "count": 2
                                        },
                                        "id": "17978823325252680",
                                        "owner": {
                                            "id": "9979057198",
                                            "is_verified": false,
                                            "profile_pic_url": "https://instagram.fala4-1.fna.fbcdn.net/vp/9a1a8a931ca1249b57a91917564f2856/5DA39AF1/t51.2885-19/44884218_345707102882519_2446069589734326272_n.jpg?_nc_ht=instagram.fala4-1.fna.fbcdn.net",
                                            "username": "shavanazta"
                                        },
                                        "text": "@kartikajylo jawabannya nyambung banget bambang. Yg ga nyambung malah penerjemahnya. Penerjemahnya malah diprotes sama warga vietnam yg ngerti bahasa inggris. Karena dia salah ngeterjemahin jawaban si ceu hennie",
                                        "viewer_has_liked": false
                                    }
                                },
                                {
                                    "node": {
                                        "created_at": 1560064100,
                                        "did_report_as_spam": false,
                                        "edge_liked_by": {
                                            "count": 0
                                        },
                                        "id": "18075609217048717",
                                        "owner": {
                                            "id": "1431592800",
                                            "is_verified": false,
                                            "profile_pic_url": "https://instagram.faal2-1.fna.fbcdn.net/vp/213ab6abf01c7b5070c6288b68450913/5DC749EE/t51.2885-19/s150x150/62153706_367907917416288_1029252504048631808_n.jpg?_nc_ht=instagram.faal2-1.fna.fbcdn.net",
                                            "username": "didisandhyka16"
                                        },
                                        "text": "@kartikajylo jawabnnya bgus, yg salah penerjemahnya. Mungkin sama kasus dgn bunga waktu interview katanya jawaban bunga bgus tpi penerjemah nya itu kurang sreg, makanya pas bunga selesai interview tuh bunga senang dan yakin dgn jawabnnya dan pas disorot ke penerjemah itu biasa aja",
                                        "viewer_has_liked": false
                                    }
                                }
                            ],
                            "page_info": {
                                "end_cursor": null,
                                "has_next_page": false
                            }
                        },
                        "id": "17905291246313286",
                        "owner": {
                            "id": "6645559688",
                            "is_verified": false,
                            "profile_pic_url": "https://instagram.faal2-1.fna.fbcdn.net/vp/b5a425d1dee55c5eec5df1ee5717002e/5DC1955C/t51.2885-19/s150x150/58468374_2191689097583346_5563063506904809472_n.jpg?_nc_ht=instagram.faal2-1.fna.fbcdn.net",
                            "username": "kartikajylo"
                        },
                        "text": "Dtnya apa jwbnya apa\ud83d\ude44\ud83d\ude44\ud83d\ude44 kok bsa ya TOP 5 ,heran",
                        "viewer_has_liked": false
                    }
                },
                {
                    "node": {
                        "created_at": 1559616041,
                        "did_report_as_spam": false,
                        "edge_liked_by": {
                            "count": 0
                        },
                        "edge_threaded_comments": {
                            "count": 7,
                            "edges": [
                                {
                                    "node": {
                                        "created_at": 1559837733,
                                        "did_report_as_spam": false,
                                        "edge_liked_by": {
                                            "count": 0
                                        },
                                        "id": "17938200121291801",
                                        "owner": {
                                            "id": "4481126315",
                                            "is_verified": false,
                                            "profile_pic_url": "https://instagram.faal2-1.fna.fbcdn.net/vp/8f132fa43fa921b1cdb97f7ff31b15c3/5D8BF199/t51.2885-19/s150x150/58909976_820624408307448_5259779442179309568_n.jpg?_nc_ht=instagram.faal2-1.fna.fbcdn.net",
                                            "username": "alanfhln_"
                                        },
                                        "text": "@mpule.kwelagobe dulu waktu di MU, pertanyaan mu apa si ci, kok gatay\ud83d\ude05",
                                        "viewer_has_liked": false
                                    }
                                },
                                {
                                    "node": {
                                        "created_at": 1559856890,
                                        "did_report_as_spam": false,
                                        "edge_liked_by": {
                                            "count": 0
                                        },
                                        "id": "17952954436282751",
                                        "owner": {
                                            "id": "6225185036",
                                            "is_verified": false,
                                            "profile_pic_url": "https://instagram.faal2-1.fna.fbcdn.net/vp/f5ddcbb3b98b27490825287b5e55ba31/5DC45A1B/t51.2885-19/s150x150/53305657_1128668000628403_6481071384414912512_n.jpg?_nc_ht=instagram.faal2-1.fna.fbcdn.net",
                                            "username": "mpule.kwelagobe"
                                        },
                                        "text": "@alanfhln_ apa pendapat mu ttg miss universe yang hamil sewaktu ia msh dalam jabatannya?  trus ga jawab ya gpp dong ceu, namanya akikah jg wanita. ya harus menjalani proses kehamilan itu sebagai selebrasi gw sebagai seorang wanita. dan jawaban gw itu menggugah hati om trump hingga menghantarkanku menjadi miss universe 1999 dan menundukkan congor pignoy cue.  aut mangap mangap mandjah",
                                        "viewer_has_liked": false
                                    }
                                },
                                {
                                    "node": {
                                        "created_at": 1559994319,
                                        "did_report_as_spam": false,
                                        "edge_liked_by": {
                                            "count": 0
                                        },
                                        "id": "17843003476481591",
                                        "owner": {
                                            "id": "8431578811",
                                            "is_verified": false,
                                            "profile_pic_url": "https://instagram.faal2-1.fna.fbcdn.net/vp/f280376716c41fdc78960b09a7cbb64c/5D8D7E8C/t51.2885-19/s150x150/64333902_2329315697122129_538111216950706176_n.jpg?_nc_ht=instagram.faal2-1.fna.fbcdn.net",
                                            "username": "reyshapratiwi_"
                                        },
                                        "text": "@mpule.kwelagobe hee bukan main mangap nya itu kayak kemasukan aset mr.supra mianmar",
                                        "viewer_has_liked": false
                                    }
                                }
                            ],
                            "page_info": {
                                "end_cursor": "QVFBVkFwVzNNVDdDV0M1UjVQYlBlNXZPY1d6aTJmV3Y1SHJta3VHUVhwNXVtUEsxY3hJUTY1UXNtb2NYRTBtV0JnRlE2MTU5dTBYOEZIX0pRR1lnUVZTRQ==",
                                "has_next_page": true
                            }
                        },
                        "id": "18055547560128337",
                        "owner": {
                            "id": "6225185036",
                            "is_verified": false,
                            "profile_pic_url": "https://instagram.faal2-1.fna.fbcdn.net/vp/f5ddcbb3b98b27490825287b5e55ba31/5DC45A1B/t51.2885-19/s150x150/53305657_1128668000628403_6481071384414912512_n.jpg?_nc_ht=instagram.faal2-1.fna.fbcdn.net",
                            "username": "mpule.kwelagobe"
                        },
                        "text": "e bentar apa sih metoo movement itu?",
                        "viewer_has_liked": false
                    }
                },
                {
                    "node": {
                        "created_at": 1559623555,
                        "did_report_as_spam": false,
                        "edge_liked_by": {
                            "count": 0
                        },
                        "edge_threaded_comments": {
                            "count": 0,
                            "edges": [],
                            "page_info": {
                                "end_cursor": null,
                                "has_next_page": false
                            }
                        },
                        "id": "17995133983230898",
                        "owner": {
                            "id": "2031447556",
                            "is_verified": false,
                            "profile_pic_url": "https://instagram.faal2-1.fna.fbcdn.net/vp/4956864ae326e0384bb74d4253c7f14b/5DC43C49/t51.2885-19/s150x150/61621957_302769223960419_1851800361128427520_n.jpg?_nc_ht=instagram.faal2-1.fna.fbcdn.net",
                            "username": "kashev___khan"
                        },
                        "text": "Pdhal hrsnya bhs English itu wajib jd syarat",
                        "viewer_has_liked": false
                    }
                },
                {
                    "node": {
                        "created_at": 1559625000,
                        "did_report_as_spam": false,
                        "edge_liked_by": {
                            "count": 0
                        },
                        "edge_threaded_comments": {
                            "count": 0,
                            "edges": [],
                            "page_info": {
                                "end_cursor": null,
                                "has_next_page": false
                            }
                        },
                        "id": "18075695515055801",
                        "owner": {
                            "id": "6311247294",
                            "is_verified": false,
                            "profile_pic_url": "https://instagram.faal2-1.fna.fbcdn.net/vp/0e857e5e921250beeb37548a318af7b7/5D8868A7/t51.2885-19/s150x150/46927051_214156826178818_3336286176981024768_n.jpg?_nc_ht=instagram.faal2-1.fna.fbcdn.net",
                            "username": "ach_ziaul09"
                        },
                        "text": "MIKROFON PELUNAS UTANGGGG\ud83c\udfb6",
                        "viewer_has_liked": false
                    }
                },
                {
                    "node": {
                        "created_at": 1559638937,
                        "did_report_as_spam": false,
                        "edge_liked_by": {
                            "count": 2
                        },
                        "edge_threaded_comments": {
                            "count": 1,
                            "edges": [
                                {
                                    "node": {
                                        "created_at": 1559994391,
                                        "did_report_as_spam": false,
                                        "edge_liked_by": {
                                            "count": 0
                                        },
                                        "id": "18073798147026813",
                                        "owner": {
                                            "id": "8431578811",
                                            "is_verified": false,
                                            "profile_pic_url": "https://instagram.faal2-1.fna.fbcdn.net/vp/f280376716c41fdc78960b09a7cbb64c/5D8D7E8C/t51.2885-19/s150x150/64333902_2329315697122129_538111216950706176_n.jpg?_nc_ht=instagram.faal2-1.fna.fbcdn.net",
                                            "username": "reyshapratiwi_"
                                        },
                                        "text": "@auwhadid gak bodoh ceu cuma mungkin grogi soalnya untuk pertama kali deseu jadi translator di MU",
                                        "viewer_has_liked": false
                                    }
                                }
                            ],
                            "page_info": {
                                "end_cursor": null,
                                "has_next_page": false
                            }
                        },
                        "id": "17994227359236312",
                        "owner": {
                            "id": "2709782338",
                            "is_verified": false,
                            "profile_pic_url": "https://instagram.faal2-1.fna.fbcdn.net/vp/897ea1af0f7c48f8cd5ae34432ab76ea/5D8C08BA/t51.2885-19/s150x150/56593829_2636268459736220_419613000534589440_n.jpg?_nc_ht=instagram.faal2-1.fna.fbcdn.net",
                            "username": "auwhadid"
                        },
                        "text": "Aku juga udah ragu sama penerjemahnya. Yg bodoh ini penerjemah nya btw",
                        "viewer_has_liked": false
                    }
                },
                {
                    "node": {
                        "created_at": 1559639160,
                        "did_report_as_spam": false,
                        "edge_liked_by": {
                            "count": 0
                        },
                        "edge_threaded_comments": {
                            "count": 1,
                            "edges": [
                                {
                                    "node": {
                                        "created_at": 1559994518,
                                        "did_report_as_spam": false,
                                        "edge_liked_by": {
                                            "count": 0
                                        },
                                        "id": "17991400708244102",
                                        "owner": {
                                            "id": "8431578811",
                                            "is_verified": false,
                                            "profile_pic_url": "https://instagram.faal2-1.fna.fbcdn.net/vp/f280376716c41fdc78960b09a7cbb64c/5D8D7E8C/t51.2885-19/s150x150/64333902_2329315697122129_538111216950706176_n.jpg?_nc_ht=instagram.faal2-1.fna.fbcdn.net",
                                            "username": "reyshapratiwi_"
                                        },
                                        "text": "@laura_borju penerusnya juga jual drama",
                                        "viewer_has_liked": false
                                    }
                                }
                            ],
                            "page_info": {
                                "end_cursor": null,
                                "has_next_page": false
                            }
                        },
                        "id": "17876515042374835",
                        "owner": {
                            "id": "4731791955",
                            "is_verified": false,
                            "profile_pic_url": "https://instagram.faal2-1.fna.fbcdn.net/vp/d87882ae1195b785a5c957c49dc88bf3/5DC462E5/t51.2885-19/s150x150/25037467_911216672361027_1828226093094535168_n.jpg?_nc_ht=instagram.faal2-1.fna.fbcdn.net",
                            "username": "laura_borju"
                        },
                        "text": "Jual drama kebanyakn .",
                        "viewer_has_liked": false
                    }
                },
                {
                    "node": {
                        "created_at": 1559702155,
                        "did_report_as_spam": false,
                        "edge_liked_by": {
                            "count": 1
                        },
                        "edge_threaded_comments": {
                            "count": 0,
                            "edges": [],
                            "page_info": {
                                "end_cursor": null,
                                "has_next_page": false
                            }
                        },
                        "id": "17990580586244981",
                        "owner": {
                            "id": "11297397001",
                            "is_verified": false,
                            "profile_pic_url": "https://instagram.faal2-1.fna.fbcdn.net/vp/ed1444eda26e61624ced3760a9402171/5DC33EBC/t51.2885-19/s150x150/62211264_608962786273917_3379534693765480448_n.jpg?_nc_ht=instagram.faal2-1.fna.fbcdn.net",
                            "username": "fadlyhedlison"
                        },
                        "text": "hadehh mendigan dia jauh better dri pada lo yg cmn bisa berkomtar",
                        "viewer_has_liked": false
                    }
                },
                {
                    "node": {
                        "created_at": 1559707077,
                        "did_report_as_spam": false,
                        "edge_liked_by": {
                            "count": 0
                        },
                        "edge_threaded_comments": {
                            "count": 0,
                            "edges": [],
                            "page_info": {
                                "end_cursor": null,
                                "has_next_page": false
                            }
                        },
                        "id": "17844142447472501",
                        "owner": {
                            "id": "11288968927",
                            "is_verified": false,
                            "profile_pic_url": "https://instagram.faal2-1.fna.fbcdn.net/vp/a3e5844c39e2f971d2d5b945351176ac/5DA46FDC/t51.2885-19/s150x150/62586023_338230590196761_4927663085902102528_n.jpg?_nc_ht=instagram.faal2-1.fna.fbcdn.net",
                            "username": "fajarhulukati"
                        },
                        "text": "Boleh nanya yg udah ad terjemahannya itu liat dimana yah?",
                        "viewer_has_liked": false
                    }
                },
                {
                    "node": {
                        "created_at": 1559835272,
                        "did_report_as_spam": false,
                        "edge_liked_by": {
                            "count": 3
                        },
                        "edge_threaded_comments": {
                            "count": 0,
                            "edges": [],
                            "page_info": {
                                "end_cursor": null,
                                "has_next_page": false
                            }
                        },
                        "id": "17879648224369912",
                        "owner": {
                            "id": "360802348",
                            "is_verified": false,
                            "profile_pic_url": "https://instagram.faal2-1.fna.fbcdn.net/vp/8c23628ba616781073014828718ba639/5DA0809A/t51.2885-19/11311203_933868483343672_237174122_a.jpg?_nc_ht=instagram.faal2-1.fna.fbcdn.net",
                            "username": "nickrawr1"
                        },
                        "text": "Kalau indo ga bisa inggris, negara onoh gives bad comment. Kalau negara lain ga bisa inggris, selalu mengacu sm jawaban janine tugonon.. Wkwk",
                        "viewer_has_liked": false
                    }
                },
                {
                    "node": {
                        "created_at": 1559921882,
                        "did_report_as_spam": false,
                        "edge_liked_by": {
                            "count": 0
                        },
                        "edge_threaded_comments": {
                            "count": 0,
                            "edges": [],
                            "page_info": {
                                "end_cursor": null,
                                "has_next_page": false
                            }
                        },
                        "id": "17886697072355514",
                        "owner": {
                            "id": "201879716",
                            "is_verified": false,
                            "profile_pic_url": "https://instagram.faal2-1.fna.fbcdn.net/vp/9627e97a2372016325274dc11d94fea4/5DC3B539/t51.2885-19/s150x150/61824630_596904574135320_1261036238152925184_n.jpg?_nc_ht=instagram.faal2-1.fna.fbcdn.net",
                            "username": "lthflyy"
                        },
                        "text": "bondol ngomong udah terlalu jauhh,,,tp interpreteur bilangnya aku rasa belom terlalu jauh\ud83e\udd23\ud83e\udd23\ud83e\udd23\ud83e\udd23",
                        "viewer_has_liked": false
                    }
                },
                {
                    "node": {
                        "created_at": 1559952714,
                        "did_report_as_spam": false,
                        "edge_liked_by": {
                            "count": 0
                        },
                        "edge_threaded_comments": {
                            "count": 1,
                            "edges": [
                                {
                                    "node": {
                                        "created_at": 1559994459,
                                        "did_report_as_spam": false,
                                        "edge_liked_by": {
                                            "count": 0
                                        },
                                        "id": "18045738061136091",
                                        "owner": {
                                            "id": "8431578811",
                                            "is_verified": false,
                                            "profile_pic_url": "https://instagram.faal2-1.fna.fbcdn.net/vp/f280376716c41fdc78960b09a7cbb64c/5D8D7E8C/t51.2885-19/s150x150/64333902_2329315697122129_538111216950706176_n.jpg?_nc_ht=instagram.faal2-1.fna.fbcdn.net",
                                            "username": "reyshapratiwi_"
                                        },
                                        "text": "@adisetyawan.n ayem from etnic mainoriti .......but now ai can du yu candu",
                                        "viewer_has_liked": false
                                    }
                                }
                            ],
                            "page_info": {
                                "end_cursor": null,
                                "has_next_page": false
                            }
                        },
                        "id": "17953324912282558",
                        "owner": {
                            "id": "1634149628",
                            "is_verified": false,
                            "profile_pic_url": "https://instagram.faal2-1.fna.fbcdn.net/vp/be4c10e66609e1c4e00887595281dc91/5D84DD81/t51.2885-19/s150x150/51906513_299641837397169_2244730546624135168_n.jpg?_nc_ht=instagram.faal2-1.fna.fbcdn.net",
                            "username": "adisetyawan.n"
                        },
                        "text": "ai ken du. yu ken duit \ud83d\udcaa",
                        "viewer_has_liked": false
                    }
                },
                {
                    "node": {
                        "created_at": 1559989562,
                        "did_report_as_spam": false,
                        "edge_liked_by": {
                            "count": 0
                        },
                        "edge_threaded_comments": {
                            "count": 0,
                            "edges": [],
                            "page_info": {
                                "end_cursor": null,
                                "has_next_page": false
                            }
                        },
                        "id": "18039930022180562",
                        "owner": {
                            "id": "11822085067",
                            "is_verified": false,
                            "profile_pic_url": "https://instagram.fala4-1.fna.fbcdn.net/vp/9a1a8a931ca1249b57a91917564f2856/5DA39AF1/t51.2885-19/44884218_345707102882519_2446069589734326272_n.jpg?_nc_ht=instagram.fala4-1.fna.fbcdn.net",
                            "username": "altanovadanang"
                        },
                        "text": "Inilah kalo place dengan cara nyogok tapi wakilnya secara public speaking belum siap. Dasar natdir cowok sok kegantengan",
                        "viewer_has_liked": false
                    }
                },
                {
                    "node": {
                        "created_at": 1559994273,
                        "did_report_as_spam": false,
                        "edge_liked_by": {
                            "count": 0
                        },
                        "edge_threaded_comments": {
                            "count": 0,
                            "edges": [],
                            "page_info": {
                                "end_cursor": null,
                                "has_next_page": false
                            }
                        },
                        "id": "17867400181398604",
                        "owner": {
                            "id": "3800134744",
                            "is_verified": false,
                            "profile_pic_url": "https://instagram.faal2-1.fna.fbcdn.net/vp/e9674d61598bb65078cc52ff2ddf4320/5D88ABB7/t51.2885-19/s150x150/26183671_1987032081511190_4714264165466767360_n.jpg?_nc_ht=instagram.faal2-1.fna.fbcdn.net",
                            "username": "almania_yahya"
                        },
                        "text": "TRANSLATENYA SALAH",
                        "viewer_has_liked": false
                    }
                }
            ],
            "page_info": {
                "end_cursor": "QVFEV1FMc1VoaEtNYVR6MENYZUROaVl0ck9FdzZQQ0xRbzBsUDd4R3JfM3RHMG52QWw5ZXA1UXhwV0t1eXlOdFZzS2x0RzI1S3o1YUpuV3ZkaDEyLWZzQg==",
                "has_next_page": true
            }
        },
        "edge_media_to_sponsor_user": {
            "edges": []
        },
        "edge_media_to_tagged_user": {
            "edges": []
        },
        "edge_web_media_to_related_media": {
            "edges": []
        },
        "encoding_status": null,
        "gating_info": null,
        "has_ranked_comments": false,
        "id": "2058106041112731923",
        "is_ad": false,
        "is_published": true,
        "is_video": true,
        "location": null,
        "media_preview": null,
        "owner": {
            "blocked_by_viewer": false,
            "followed_by_viewer": false,
            "full_name": "Pageant In Diversity",
            "has_blocked_viewer": false,
            "id": "5865155797",
            "is_private": false,
            "is_unpublished": false,
            "is_verified": false,
            "profile_pic_url": "https://instagram.faal2-1.fna.fbcdn.net/vp/0e1bfbf08ab13e68642dd05ef7228cd3/5D944599/t51.2885-19/s150x150/44258640_185157779051276_4896973551707357184_n.jpg?_nc_ht=instagram.faal2-1.fna.fbcdn.net",
            "requested_by_viewer": false,
            "username": "pageant.ind"
        },
        "product_type": "feed",
        "shortcode": "ByP3IpCnCET",
        "should_log_client_event": false,
        "taken_at_timestamp": 1559565551,
        "thumbnail_resources": [
            {
                "config_height": 150,
                "config_width": 150,
                "src": "https://instagram.faal2-1.fna.fbcdn.net/vp/2e9ac87745744b54abd57b3d0e14546e/5D09F567/t51.2885-15/e35/c157.0.406.406a/s150x150/61342316_2412669592087766_193945895401469761_n.jpg?_nc_ht=instagram.faal2-1.fna.fbcdn.net"
            },
            {
                "config_height": 240,
                "config_width": 240,
                "src": "https://instagram.faal2-1.fna.fbcdn.net/vp/83a2cada897e1e44b6d0b38cccba5991/5D0988AD/t51.2885-15/e35/c157.0.406.406a/s240x240/61342316_2412669592087766_193945895401469761_n.jpg?_nc_ht=instagram.faal2-1.fna.fbcdn.net"
            },
            {
                "config_height": 320,
                "config_width": 320,
                "src": "https://instagram.faal2-1.fna.fbcdn.net/vp/1f98b21c387f9255271f8048a2d481e6/5D0990D7/t51.2885-15/e35/c157.0.406.406a/s320x320/61342316_2412669592087766_193945895401469761_n.jpg?_nc_ht=instagram.faal2-1.fna.fbcdn.net"
            },
            {
                "config_height": 480,
                "config_width": 480,
                "src": "https://instagram.faal2-1.fna.fbcdn.net/vp/026a13f05ce5203206054c32da75371d/5D099642/t51.2885-15/e35/c157.0.406.406a/61342316_2412669592087766_193945895401469761_n.jpg?_nc_ht=instagram.faal2-1.fna.fbcdn.net"
            },
            {
                "config_height": 640,
                "config_width": 640,
                "src": "https://instagram.faal2-1.fna.fbcdn.net/vp/026a13f05ce5203206054c32da75371d/5D099642/t51.2885-15/e35/c157.0.406.406a/61342316_2412669592087766_193945895401469761_n.jpg?_nc_ht=instagram.faal2-1.fna.fbcdn.net"
            }
        ],
        "thumbnail_src": "https://instagram.faal2-1.fna.fbcdn.net/vp/026a13f05ce5203206054c32da75371d/5D099642/t51.2885-15/e35/c157.0.406.406a/61342316_2412669592087766_193945895401469761_n.jpg?_nc_ht=instagram.faal2-1.fna.fbcdn.net",
        "title": "",
        "tracking_token": "eyJ2ZXJzaW9uIjo1LCJwYXlsb2FkIjp7ImlzX2FuYWx5dGljc190cmFja2VkIjp0cnVlLCJ1dWlkIjoiMzNkM2EyZWNjNzY0NDk3NGFiNDVkMThhOGQzMDZiMTcyMDU4MTA2MDQxMTEyNzMxOTIzIn0sInNpZ25hdHVyZSI6IiJ9",
        "video_duration": 49.37,
        "video_url": "https://scontent.cdninstagram.com/vp/04df33a7a4ec4865ef573b1cca9eb8ab/5D09A813/t50.2886-16/62022698_2463883916969788_2425903945185492992_n.mp4?_nc_ht=scontent.cdninstagram.com",
        "video_view_count": 25754,
        "viewer_can_reshare": true,
        "viewer_has_liked": false,
        "viewer_has_saved": false,
        "viewer_has_saved_to_collection": false,
        "viewer_in_photo_of_you": false
    }
}