{
    "instaloader": {
        "node_type": "Post",
        "version": "4.2.8"
    },
    "node": {
        "__typename": "GraphImage",
        "accessibility_caption": "Image may contain: text",
        "comments_disabled": false,
        "dimensions": {
            "height": 598,
            "width": 640
        },
        "display_url": "https://instagram.faal2-1.fna.fbcdn.net/vp/989c3c496cf6447c5507cd4ecf38b0ff/5D91E132/t51.2885-15/e35/62242823_339179073436974_4233006430709836707_n.jpg?_nc_ht=instagram.faal2-1.fna.fbcdn.net",
        "edge_liked_by": {
            "count": 8
        },
        "edge_media_preview_like": {
            "count": 8
        },
        "edge_media_to_caption": {
            "edges": [
                {
                    "node": {
                        "text": "\ud83d\udeabHelp End Sex Trafficking\ud83d\udeab#HumanTrafficking#StopHumanTrafficking#StopSexTrafficking#StopChildSexualAbuse#MeToo#Homelessness#Homelessnessawareness#ChildSexualExploitation#ChildSexualAbuse#Nonprofit#Womensupportingwomen#Bossladies#BossChickGirlBoss#Goaldigger#Girlbosslife#Girlbossgang#Bosschick#Bossladies#Bossgirl\u00a0#Chicagobloggers#Girlgang\u00a0#Atlanta#Empoweringwomen#Nonprofitorganization#ChicagoEntrepreneurs#Blackgirlmagic#Womenwhohustle#Bossup#Womeninbusiness#Goalgetter#Businesswomen"
                    }
                }
            ]
        },
        "edge_media_to_comment": {
            "count": 0
        },
        "id": "2063403692464737922",
        "is_video": false,
        "owner": {
            "id": "12143053962"
        },
        "shortcode": "ByirrnVlw6C",
        "taken_at_timestamp": 1560196909,
        "thumbnail_resources": [
            {
                "config_height": 150,
                "config_width": 150,
                "src": "https://instagram.faal2-1.fna.fbcdn.net/vp/0b610f9e49c70864dfadb60f8f06a5a4/5D8A68E8/t51.2885-15/e35/c18.0.520.520a/s150x150/62242823_339179073436974_4233006430709836707_n.jpg?_nc_ht=instagram.faal2-1.fna.fbcdn.net"
            },
            {
                "config_height": 240,
                "config_width": 240,
                "src": "https://instagram.faal2-1.fna.fbcdn.net/vp/240851f9cb3fb4a448e3a2c1103d26ef/5D8A99A2/t51.2885-15/e35/c18.0.520.520a/s240x240/62242823_339179073436974_4233006430709836707_n.jpg?_nc_ht=instagram.faal2-1.fna.fbcdn.net"
            },
            {
                "config_height": 320,
                "config_width": 320,
                "src": "https://instagram.faal2-1.fna.fbcdn.net/vp/06b5ff01ccd572aad6932d264f85e01f/5DC35518/t51.2885-15/e35/c18.0.520.520a/s320x320/62242823_339179073436974_4233006430709836707_n.jpg?_nc_ht=instagram.faal2-1.fna.fbcdn.net"
            },
            {
                "config_height": 480,
                "config_width": 480,
                "src": "https://instagram.faal2-1.fna.fbcdn.net/vp/b1be1ce60d924a31dc3f68178c2f95ad/5D86B842/t51.2885-15/e35/c18.0.520.520a/s480x480/62242823_339179073436974_4233006430709836707_n.jpg?_nc_ht=instagram.faal2-1.fna.fbcdn.net"
            },
            {
                "config_height": 640,
                "config_width": 640,
                "src": "https://instagram.faal2-1.fna.fbcdn.net/vp/7077d8845984c82ad2f5cfb296830269/5D83CD8E/t51.2885-15/e35/c18.0.520.520a/62242823_339179073436974_4233006430709836707_n.jpg?_nc_ht=instagram.faal2-1.fna.fbcdn.net"
            }
        ],
        "thumbnail_src": "https://instagram.faal2-1.fna.fbcdn.net/vp/7077d8845984c82ad2f5cfb296830269/5D83CD8E/t51.2885-15/e35/c18.0.520.520a/62242823_339179073436974_4233006430709836707_n.jpg?_nc_ht=instagram.faal2-1.fna.fbcdn.net"
    }
}