{
    "instaloader": {
        "node_type": "Post",
        "version": "4.2.8"
    },
    "node": {
        "__typename": "GraphSidecar",
        "accessibility_caption": "Image may contain: text",
        "caption_is_edited": false,
        "comments_disabled": false,
        "dimensions": {
            "height": 937,
            "width": 750
        },
        "display_resources": [
            {
                "config_height": 800,
                "config_width": 640,
                "src": "https://instagram.faal2-1.fna.fbcdn.net/vp/f5c31b4c9b8657c1115e2dfbd43cbd9c/5DC2C396/t51.2885-15/sh0.08/e35/p640x640/60040130_852483505107645_6545925347581032234_n.jpg?_nc_ht=instagram.faal2-1.fna.fbcdn.net"
            },
            {
                "config_height": 937,
                "config_width": 750,
                "src": "https://instagram.faal2-1.fna.fbcdn.net/vp/5e5043034a2f85bd61365b4f5fcfe129/5DC70860/t51.2885-15/e35/60040130_852483505107645_6545925347581032234_n.jpg?_nc_ht=instagram.faal2-1.fna.fbcdn.net"
            },
            {
                "config_height": 1350,
                "config_width": 1080,
                "src": "https://instagram.faal2-1.fna.fbcdn.net/vp/5e5043034a2f85bd61365b4f5fcfe129/5DC70860/t51.2885-15/e35/60040130_852483505107645_6545925347581032234_n.jpg?_nc_ht=instagram.faal2-1.fna.fbcdn.net"
            }
        ],
        "display_url": "https://instagram.faal2-1.fna.fbcdn.net/vp/5e5043034a2f85bd61365b4f5fcfe129/5DC70860/t51.2885-15/e35/60040130_852483505107645_6545925347581032234_n.jpg?_nc_ht=instagram.faal2-1.fna.fbcdn.net",
        "edge_liked_by": {
            "count": 66
        },
        "edge_media_preview_comment": {
            "count": 0,
            "edges": []
        },
        "edge_media_preview_like": {
            "count": 66,
            "edges": []
        },
        "edge_media_to_caption": {
            "edges": [
                {
                    "node": {
                        "text": "\uc7ac\uc784\uc6a9 \ucde8\uc18c \ubabb\ud55c\ub2e4\uace0??.. \ubbfc\uc8fc\uc131\uc2e0 \ub2e4 \uc8fd\uc5c8\ub2e4\ud83d\udc4a\n\n#\uc131\uc2e0\uc5ec\ub300_\ubbf8\ud22c #withyou #\ud604\uc2e4\uc74c #metoo_meansyou #MeToo"
                    }
                }
            ]
        },
        "edge_media_to_comment": {
            "count": 0
        },
        "edge_media_to_parent_comment": {
            "count": 0,
            "edges": [],
            "page_info": {
                "end_cursor": null,
                "has_next_page": false
            }
        },
        "edge_media_to_sponsor_user": {
            "edges": []
        },
        "edge_media_to_tagged_user": {
            "edges": []
        },
        "edge_sidecar_to_children": {
            "edges": [
                {
                    "node": {
                        "__typename": "GraphImage",
                        "accessibility_caption": "Image may contain: text",
                        "dimensions": {
                            "height": 937,
                            "width": 750
                        },
                        "display_resources": [
                            {
                                "config_height": 800,
                                "config_width": 640,
                                "src": "https://instagram.faal2-1.fna.fbcdn.net/vp/f5c31b4c9b8657c1115e2dfbd43cbd9c/5DC2C396/t51.2885-15/sh0.08/e35/p640x640/60040130_852483505107645_6545925347581032234_n.jpg?_nc_ht=instagram.faal2-1.fna.fbcdn.net"
                            },
                            {
                                "config_height": 937,
                                "config_width": 750,
                                "src": "https://instagram.faal2-1.fna.fbcdn.net/vp/5e5043034a2f85bd61365b4f5fcfe129/5DC70860/t51.2885-15/e35/60040130_852483505107645_6545925347581032234_n.jpg?_nc_ht=instagram.faal2-1.fna.fbcdn.net"
                            },
                            {
                                "config_height": 1350,
                                "config_width": 1080,
                                "src": "https://instagram.faal2-1.fna.fbcdn.net/vp/5e5043034a2f85bd61365b4f5fcfe129/5DC70860/t51.2885-15/e35/60040130_852483505107645_6545925347581032234_n.jpg?_nc_ht=instagram.faal2-1.fna.fbcdn.net"
                            }
                        ],
                        "display_url": "https://instagram.faal2-1.fna.fbcdn.net/vp/5e5043034a2f85bd61365b4f5fcfe129/5DC70860/t51.2885-15/e35/60040130_852483505107645_6545925347581032234_n.jpg?_nc_ht=instagram.faal2-1.fna.fbcdn.net",
                        "edge_media_to_tagged_user": {
                            "edges": []
                        },
                        "gating_info": null,
                        "id": "2050859897742160280",
                        "is_video": false,
                        "media_preview": null,
                        "shortcode": "Bx2HjYJA_GY",
                        "should_log_client_event": false,
                        "tracking_token": "eyJ2ZXJzaW9uIjo1LCJwYXlsb2FkIjp7ImlzX2FuYWx5dGljc190cmFja2VkIjpmYWxzZSwidXVpZCI6ImFhZTEyNzFkYzRkNzQ0NDE4MDJiOWUyYzRlYTcyMDJiMjA1MDg1OTg5Nzc0MjE2MDI4MCJ9LCJzaWduYXR1cmUiOiIifQ=="
                    }
                },
                {
                    "node": {
                        "__typename": "GraphImage",
                        "accessibility_caption": "Image may contain: text",
                        "dimensions": {
                            "height": 937,
                            "width": 750
                        },
                        "display_resources": [
                            {
                                "config_height": 800,
                                "config_width": 640,
                                "src": "https://instagram.faal2-1.fna.fbcdn.net/vp/7729cc3b4465ec08ac62da52e4d47fd9/5DC64B20/t51.2885-15/sh0.08/e35/p640x640/60486436_112800779956729_8413856085329391983_n.jpg?_nc_ht=instagram.faal2-1.fna.fbcdn.net"
                            },
                            {
                                "config_height": 937,
                                "config_width": 750,
                                "src": "https://instagram.faal2-1.fna.fbcdn.net/vp/7c1d8e1084e263e33c1f9cfc45da8c4c/5DA089D6/t51.2885-15/e35/60486436_112800779956729_8413856085329391983_n.jpg?_nc_ht=instagram.faal2-1.fna.fbcdn.net"
                            },
                            {
                                "config_height": 1350,
                                "config_width": 1080,
                                "src": "https://instagram.faal2-1.fna.fbcdn.net/vp/7c1d8e1084e263e33c1f9cfc45da8c4c/5DA089D6/t51.2885-15/e35/60486436_112800779956729_8413856085329391983_n.jpg?_nc_ht=instagram.faal2-1.fna.fbcdn.net"
                            }
                        ],
                        "display_url": "https://instagram.faal2-1.fna.fbcdn.net/vp/7c1d8e1084e263e33c1f9cfc45da8c4c/5DA089D6/t51.2885-15/e35/60486436_112800779956729_8413856085329391983_n.jpg?_nc_ht=instagram.faal2-1.fna.fbcdn.net",
                        "edge_media_to_tagged_user": {
                            "edges": []
                        },
                        "gating_info": null,
                        "id": "2050859897733549213",
                        "is_video": false,
                        "media_preview": null,
                        "shortcode": "Bx2HjYIgIyd",
                        "should_log_client_event": false,
                        "tracking_token": "eyJ2ZXJzaW9uIjo1LCJwYXlsb2FkIjp7ImlzX2FuYWx5dGljc190cmFja2VkIjpmYWxzZSwidXVpZCI6ImFhZTEyNzFkYzRkNzQ0NDE4MDJiOWUyYzRlYTcyMDJiMjA1MDg1OTg5NzczMzU0OTIxMyJ9LCJzaWduYXR1cmUiOiIifQ=="
                    }
                }
            ]
        },
        "edge_web_media_to_related_media": {
            "edges": []
        },
        "gating_info": null,
        "has_ranked_comments": false,
        "id": "2050859909863443954",
        "is_ad": false,
        "is_video": false,
        "location": null,
        "media_preview": null,
        "owner": {
            "blocked_by_viewer": false,
            "followed_by_viewer": false,
            "full_name": "\ud55c\uc8fc",
            "has_blocked_viewer": false,
            "id": "5363581815",
            "is_private": false,
            "is_unpublished": false,
            "is_verified": false,
            "profile_pic_url": "https://instagram.faal2-1.fna.fbcdn.net/vp/22000ba77010158440d33d85b788b9c2/5D897391/t51.2885-19/s150x150/62017450_365511174095431_8145113676785909760_n.jpg?_nc_ht=instagram.faal2-1.fna.fbcdn.net",
            "requested_by_viewer": false,
            "username": "zzu.mp4"
        },
        "shortcode": "Bx2HjjbgA3y",
        "should_log_client_event": false,
        "taken_at_timestamp": 1558701574,
        "thumbnail_resources": [
            {
                "config_height": 150,
                "config_width": 150,
                "src": "https://instagram.faal2-1.fna.fbcdn.net/vp/d5a11a3a9ac23f706b532cbf0c5e2aa0/5DC2D89D/t51.2885-15/e35/c0.90.720.720/s150x150/60040130_852483505107645_6545925347581032234_n.jpg?_nc_ht=instagram.faal2-1.fna.fbcdn.net"
            },
            {
                "config_height": 240,
                "config_width": 240,
                "src": "https://instagram.faal2-1.fna.fbcdn.net/vp/290db6d3e0797355fe46d12df396d5fe/5D84E2D7/t51.2885-15/e35/c0.90.720.720/s240x240/60040130_852483505107645_6545925347581032234_n.jpg?_nc_ht=instagram.faal2-1.fna.fbcdn.net"
            },
            {
                "config_height": 320,
                "config_width": 320,
                "src": "https://instagram.faal2-1.fna.fbcdn.net/vp/93206f275ff2b2db77ec531b65f3a674/5D89EB6D/t51.2885-15/e35/c0.90.720.720/s320x320/60040130_852483505107645_6545925347581032234_n.jpg?_nc_ht=instagram.faal2-1.fna.fbcdn.net"
            },
            {
                "config_height": 480,
                "config_width": 480,
                "src": "https://instagram.faal2-1.fna.fbcdn.net/vp/6ad4eeed00091dbfb45d4a84e77571a1/5DC75137/t51.2885-15/e35/c0.90.720.720/s480x480/60040130_852483505107645_6545925347581032234_n.jpg?_nc_ht=instagram.faal2-1.fna.fbcdn.net"
            },
            {
                "config_height": 640,
                "config_width": 640,
                "src": "https://instagram.faal2-1.fna.fbcdn.net/vp/8f09c396c03ee36bcf51965902d11cfc/5DC744D4/t51.2885-15/sh0.08/e35/c0.90.720.720/s640x640/60040130_852483505107645_6545925347581032234_n.jpg?_nc_ht=instagram.faal2-1.fna.fbcdn.net"
            }
        ],
        "thumbnail_src": "https://instagram.faal2-1.fna.fbcdn.net/vp/8f09c396c03ee36bcf51965902d11cfc/5DC744D4/t51.2885-15/sh0.08/e35/c0.90.720.720/s640x640/60040130_852483505107645_6545925347581032234_n.jpg?_nc_ht=instagram.faal2-1.fna.fbcdn.net",
        "tracking_token": "eyJ2ZXJzaW9uIjo1LCJwYXlsb2FkIjp7ImlzX2FuYWx5dGljc190cmFja2VkIjpmYWxzZSwidXVpZCI6ImFhZTEyNzFkYzRkNzQ0NDE4MDJiOWUyYzRlYTcyMDJiMjA1MDg1OTkwOTg2MzQ0Mzk1NCJ9LCJzaWduYXR1cmUiOiIifQ==",
        "viewer_can_reshare": true,
        "viewer_has_liked": false,
        "viewer_has_saved": false,
        "viewer_has_saved_to_collection": false,
        "viewer_in_photo_of_you": false
    }
}